{
  "best_epoch": 18,
  "best_metrics": {
    "accuracy": 0.6389721534384639,
    "brier_score": 0.5782808661460876,
    "cohen_kappa": 0.5641743499945593,
    "ece": 0.2188125244651341,
    "loss": 2.0144604284688037,
    "macro_f1": 0.5245876596864762,
    "macro_pr_auc_ovr": 0.5677529439081181,
    "macro_roc_auc_ovr": 0.9416653427163512,
    "micro_f1": 0.6389721534384639,
    "n_classes_missing_neg": 0,
    "n_classes_missing_pos": 2,
    "n_classes_scored": 84,
    "n_classes_total": 86,
    "n_samples": 46038,
    "nll": 1.9156368970870972,
    "nll_loss": 1.9381826082751465,
    "objective_loss": 2.0144604284688037,
    "tail_class_ids": [
      12,
      30,
      64,
      85,
      25,
      34,
      41,
      27,
      51,
      42,
      78,
      43,
      40,
      0,
      61,
      6,
      37,
      49
    ],
    "tail_definition": "bottom_20pct_train_support_including_zero",
    "tail_k": 18,
    "tail_macro_pr_auc_ovr": 0.2479232094020014,
    "tail_n_classes_scored": 16
  },
  "history": [
    {
      "drw_on": false,
      "epoch": 1,
      "lr": 0.001,
      "train_loss": 1.1135708711217351,
      "train_objective_loss": 1.1135708711217351,
      "train_plain_nll_loss": 1.1135708711217351,
      "train_weight_diverse_batches_pct": 0.0,
      "valid_loss": 1.4899602112469092,
      "valid_macro_pr_auc_ovr": 0.4342344138880934,
      "valid_macro_roc_auc_ovr": 0.9078517607225326
    },
    {
      "drw_on": false,
      "epoch": 2,
      "lr": 0.001,
      "train_loss": 0.6169584297754681,
      "train_objective_loss": 0.6169584297754681,
      "train_plain_nll_loss": 0.6169584297754681,
      "train_weight_diverse_batches_pct": 0.0,
      "valid_loss": 1.4271719645726764,
      "valid_macro_pr_auc_ovr": 0.48363105199050566,
      "valid_macro_roc_auc_ovr": 0.9423447166678086
    },
    {
      "drw_on": false,
      "epoch": 3,
      "lr": 0.001,
      "train_loss": 0.5118307149811588,
      "train_objective_loss": 0.5118307149811588,
      "train_plain_nll_loss": 0.5118307149811588,
      "train_weight_diverse_batches_pct": 0.0,
      "valid_loss": 1.4745914269562543,
      "valid_macro_pr_auc_ovr": 0.5213755399555753,
      "valid_macro_roc_auc_ovr": 0.9476247563196135
    },
    {
      "drw_on": false,
      "epoch": 4,
      "lr": 0.001,
      "train_loss": 0.4548400691707288,
      "train_objective_loss": 0.4548400691707288,
      "train_plain_nll_loss": 0.4548400691707288,
      "train_weight_diverse_batches_pct": 0.0,
      "valid_loss": 1.624063481153096,
      "valid_macro_pr_auc_ovr": 0.5230012663834523,
      "valid_macro_roc_auc_ovr": 0.9428299341970359
    },
    {
      "drw_on": false,
      "epoch": 5,
      "lr": 0.001,
      "train_loss": 0.42437850498929164,
      "train_objective_loss": 0.42437850498929164,
      "train_plain_nll_loss": 0.42437850498929164,
      "train_weight_diverse_batches_pct": 0.0,
      "valid_loss": 1.5806721508816273,
      "valid_macro_pr_auc_ovr": 0.5337815334153605,
      "valid_macro_roc_auc_ovr": 0.944522275881916
    },
    {
      "drw_on": false,
      "epoch": 6,
      "lr": 0.001,
      "train_loss": 0.3973098254099114,
      "train_objective_loss": 0.3973098254099114,
      "train_plain_nll_loss": 0.3973098254099114,
      "train_weight_diverse_batches_pct": 0.0,
      "valid_loss": 1.5968849978286834,
      "valid_macro_pr_auc_ovr": 0.5435430749069718,
      "valid_macro_roc_auc_ovr": 0.9412182772625347
    },
    {
      "drw_on": false,
      "epoch": 7,
      "lr": 0.001,
      "train_loss": 0.3743408362294459,
      "train_objective_loss": 0.3743408362294459,
      "train_plain_nll_loss": 0.3743408362294459,
      "train_weight_diverse_batches_pct": 0.0,
      "valid_loss": 1.687729309356007,
      "valid_macro_pr_auc_ovr": 0.5416224456972456,
      "valid_macro_roc_auc_ovr": 0.9400483218344517
    },
    {
      "drw_on": false,
      "epoch": 8,
      "lr": 0.001,
      "train_loss": 0.36185222420641805,
      "train_objective_loss": 0.36185222420641805,
      "train_plain_nll_loss": 0.36185222420641805,
      "train_weight_diverse_batches_pct": 0.0,
      "valid_loss": 1.7402300867592513,
      "valid_macro_pr_auc_ovr": 0.5463514842399831,
      "valid_macro_roc_auc_ovr": 0.9388737540943319
    },
    {
      "drw_on": false,
      "epoch": 9,
      "lr": 0.001,
      "train_loss": 0.35119875443716586,
      "train_objective_loss": 0.35119875443716586,
      "train_plain_nll_loss": 0.35119875443716586,
      "train_weight_diverse_batches_pct": 0.0,
      "valid_loss": 1.6671478919323346,
      "valid_macro_pr_auc_ovr": 0.5450407847235139,
      "valid_macro_roc_auc_ovr": 0.9433385666510598
    },
    {
      "drw_on": false,
      "epoch": 10,
      "lr": 0.001,
      "train_loss": 0.3415422637415422,
      "train_objective_loss": 0.3415422637415422,
      "train_plain_nll_loss": 0.3415422637415422,
      "train_weight_diverse_batches_pct": 0.0,
      "valid_loss": 1.76461705430676,
      "valid_macro_pr_auc_ovr": 0.5423125194571803,
      "valid_macro_roc_auc_ovr": 0.9383089217240291
    },
    {
      "drw_on": false,
      "epoch": 11,
      "lr": 0.001,
      "train_loss": 0.3283820385755397,
      "train_objective_loss": 0.3283820385755397,
      "train_plain_nll_loss": 0.3283820385755397,
      "train_weight_diverse_batches_pct": 0.0,
      "valid_loss": 1.70562342305525,
      "valid_macro_pr_auc_ovr": 0.5494491389934281,
      "valid_macro_roc_auc_ovr": 0.9413064175025628
    },
    {
      "drw_on": false,
      "epoch": 12,
      "lr": 0.001,
      "train_loss": 0.3211992178148677,
      "train_objective_loss": 0.3211992178148677,
      "train_plain_nll_loss": 0.3211992178148677,
      "train_weight_diverse_batches_pct": 0.0,
      "valid_loss": 1.790901352168217,
      "valid_macro_pr_auc_ovr": 0.5577440616484541,
      "valid_macro_roc_auc_ovr": 0.9397585462790207
    },
    {
      "drw_on": false,
      "epoch": 13,
      "lr": 0.001,
      "train_loss": 0.310466493171278,
      "train_objective_loss": 0.310466493171278,
      "train_plain_nll_loss": 0.310466493171278,
      "train_weight_diverse_batches_pct": 0.0,
      "valid_loss": 1.868230953753691,
      "valid_macro_pr_auc_ovr": 0.551409758092005,
      "valid_macro_roc_auc_ovr": 0.9386978753295594
    },
    {
      "drw_on": false,
      "epoch": 14,
      "lr": 0.001,
      "train_loss": 0.3077489631330654,
      "train_objective_loss": 0.3077489631330654,
      "train_plain_nll_loss": 0.3077489631330654,
      "train_weight_diverse_batches_pct": 0.0,
      "valid_loss": 1.8274834752781954,
      "valid_macro_pr_auc_ovr": 0.5472923326625059,
      "valid_macro_roc_auc_ovr": 0.9360904485167058
    },
    {
      "drw_class_weight_max": 4.0,
      "drw_class_weight_mean": 0.9293866753578186,
      "drw_class_weight_min": 0.0,
      "drw_on": true,
      "epoch": 15,
      "lr": 0.0002,
      "train_loss": 0.27279704103082386,
      "train_objective_loss": 0.27279704103082386,
      "train_plain_nll_loss": 0.2602754586116799,
      "train_weight_diverse_batches_pct": 99.81343283582089,
      "valid_loss": 1.9614066206728937,
      "valid_macro_pr_auc_ovr": 0.557061218058705,
      "valid_macro_roc_auc_ovr": 0.9407032328762375
    },
    {
      "drw_class_weight_max": 4.0,
      "drw_class_weight_mean": 0.9293866753578186,
      "drw_class_weight_min": 0.0,
      "drw_on": true,
      "epoch": 16,
      "lr": 0.0002,
      "train_loss": 0.24921034664751615,
      "train_objective_loss": 0.24921034664751615,
      "train_plain_nll_loss": 0.24041076120686133,
      "train_weight_diverse_batches_pct": 99.90671641791045,
      "valid_loss": 2.031406008579412,
      "valid_macro_pr_auc_ovr": 0.5604128355474328,
      "valid_macro_roc_auc_ovr": 0.9401625257346166
    },
    {
      "drw_class_weight_max": 4.0,
      "drw_class_weight_mean": 0.9293866753578186,
      "drw_class_weight_min": 0.0,
      "drw_on": true,
      "epoch": 17,
      "lr": 0.0002,
      "train_loss": 0.23843840339761507,
      "train_objective_loss": 0.23843840339761507,
      "train_plain_nll_loss": 0.23486482968462227,
      "train_weight_diverse_batches_pct": 100.0,
      "valid_loss": 2.031223628149029,
      "valid_macro_pr_auc_ovr": 0.5619579409245805,
      "valid_macro_roc_auc_ovr": 0.9404366288204155
    },
    {
      "drw_class_weight_max": 4.0,
      "drw_class_weight_mean": 0.9293866753578186,
      "drw_class_weight_min": 0.0,
      "drw_on": true,
      "epoch": 18,
      "lr": 0.0002,
      "train_loss": 0.23358913607503903,
      "train_objective_loss": 0.23358913607503903,
      "train_plain_nll_loss": 0.23182351195617815,
      "train_weight_diverse_batches_pct": 100.0,
      "valid_loss": 2.0144604284688037,
      "valid_macro_pr_auc_ovr": 0.5677529439081181,
      "valid_macro_roc_auc_ovr": 0.9416653427163512
    },
    {
      "drw_class_weight_max": 4.0,
      "drw_class_weight_mean": 0.9293866753578186,
      "drw_class_weight_min": 0.0,
      "drw_on": true,
      "epoch": 19,
      "lr": 0.0002,
      "train_loss": 0.2262091290462315,
      "train_objective_loss": 0.2262091290462315,
      "train_plain_nll_loss": 0.22351849583340128,
      "train_weight_diverse_batches_pct": 100.0,
      "valid_loss": 2.073394817074259,
      "valid_macro_pr_auc_ovr": 0.562252998275617,
      "valid_macro_roc_auc_ovr": 0.9419132438181608
    },
    {
      "drw_class_weight_max": 4.0,
      "drw_class_weight_mean": 0.9293866753578186,
      "drw_class_weight_min": 0.0,
      "drw_on": true,
      "epoch": 20,
      "lr": 0.0002,
      "train_loss": 0.22683275191787017,
      "train_objective_loss": 0.22683275191787017,
      "train_plain_nll_loss": 0.22333245296395865,
      "train_weight_diverse_batches_pct": 100.0,
      "valid_loss": 2.0386343872657458,
      "valid_macro_pr_auc_ovr": 0.563479580845552,
      "valid_macro_roc_auc_ovr": 0.9423362931750945
    }
  ]
}